{
  "project_info": {
    "project_number": "680244124164",
    "project_id": "twittertraining001",
    "storage_bucket": "twittertraining001.appspot.com"
  },
  "client": [
    {
      "client_info": {
        "mobilesdk_app_id": "1:680244124164:android:dd3350f176ad357e333351",
        "android_client_info": {
          "package_name": "com.example.twittertraining001"
        }
      },
      "oauth_client": [
        {
          "client_id": "680244124164-hi5eqhod7mlimaqklpiebnahadj1v7q6.apps.googleusercontent.com",
          "client_type": 3
        }
      ],
      "api_key": [
        {
          "current_key": "AIzaSyA67_Dk19YsYhIDw6fhE7uB3vV2IbHz7Ro"
        }
      ],
      "services": {
        "appinvite_service": {
          "other_platform_oauth_client": [
            {
              "client_id": "680244124164-hi5eqhod7mlimaqklpiebnahadj1v7q6.apps.googleusercontent.com",
              "client_type": 3
            }
          ]
        }
      }
    }
  ],
  "configuration_version": "1"
}